{"version":1,"sources":[{"meta":{"id":"20260616-211412-uyu5","dateStart":"2026-06-17T02:14:12.000Z","dateEnd":"2026-06-17T02:57:35.000Z","generatedAt":"2026-06-17T03:10:22.147Z"},"stats":{"commanderStats":{"rows":[{"key":"Opticz.7029","account":"Opticz.7029","characterNames":["Get On Me","Jokajo"],"profession":"Troubadour","fights":11,"kills":10,"downs":51,"commanderDeaths":3,"alliesDead":51,"wins":1,"losses":10}]},"attendanceData":[{"account":"Alatreon.1946","characterNames":["Alatreon Unendlich"],"combatTimeMs":521697,"squadTimeMs":2602902,"classTimes":[{"profession":"Luminary","timeMs":521697}]},{"account":"Celestiaallure.8472","characterNames":["Celestia Allure"],"combatTimeMs":663873,"squadTimeMs":2602902,"classTimes":[{"profession":"Tempest","timeMs":663873}]},{"account":"Chewy.5329","characterNames":["Aegisbane"],"combatTimeMs":732595,"squadTimeMs":2602902,"classTimes":[{"profession":"Firebrand","timeMs":732595}]},{"account":"curinga.6104","characterNames":["Sea Kalm"],"combatTimeMs":732595,"squadTimeMs":2602902,"classTimes":[{"profession":"Luminary","timeMs":732595}]},{"account":"DanIsMyNewName.9826","characterNames":["Dan Is A Name"],"combatTimeMs":695294,"squadTimeMs":2602902,"classTimes":[{"profession":"Harbinger","timeMs":695294}]},{"account":"DoctorBus.8932","characterNames":["Doktor Bus","Unclean Bus"],"combatTimeMs":657929,"squadTimeMs":2602902,"classTimes":[{"profession":"Reaper","timeMs":409881},{"profession":"Warrior","timeMs":248048}]},{"account":"EternalEndless.7695","characterNames":["Endless S"],"combatTimeMs":719861,"squadTimeMs":2602902,"classTimes":[{"profession":"Harbinger","timeMs":620791},{"profession":"Necromancer","timeMs":99070}]},{"account":"Jaxx.8016","characterNames":["Jaxx Wild"],"combatTimeMs":672998,"squadTimeMs":2602902,"classTimes":[{"profession":"Druid","timeMs":672998}]},{"account":"KaiDarius.8723","characterNames":["Lucent Dreams"],"combatTimeMs":529862,"squadTimeMs":2602902,"classTimes":[{"profession":"Chronomancer","timeMs":529862}]},{"account":"katoki.7869","characterNames":["Luna Du Courte"],"combatTimeMs":684532,"squadTimeMs":2602902,"classTimes":[{"profession":"Druid","timeMs":684532}]},{"account":"Kricer.7253","characterNames":["Let It Krice"],"combatTimeMs":704487,"squadTimeMs":2602902,"classTimes":[{"profession":"Troubadour","timeMs":704487}]},{"account":"LFOsc.8930","characterNames":["Am I Oscuro"],"combatTimeMs":640931,"squadTimeMs":2602902,"classTimes":[{"profession":"Chronomancer","timeMs":640931}]},{"account":"lightofday.9173","characterNames":["Light Algz"],"combatTimeMs":707017,"squadTimeMs":2602902,"classTimes":[{"profession":"Firebrand","timeMs":707017}]},{"account":"MasterVance.6201","characterNames":["Van Snacks"],"combatTimeMs":571790,"squadTimeMs":2602902,"classTimes":[{"profession":"Reaper","timeMs":571790}]},{"account":"MoonRaven.3142","characterNames":["Illusive Heart"],"combatTimeMs":665729,"squadTimeMs":2602902,"classTimes":[{"profession":"Troubadour","timeMs":665729}]},{"account":"Nina.9521","characterNames":["Labubù"],"combatTimeMs":719679,"squadTimeMs":2602902,"classTimes":[{"profession":"Scourge","timeMs":719679}]},{"account":"Opticz.7029","characterNames":["Get On Me","Jokajo"],"combatTimeMs":675797,"squadTimeMs":2602902,"classTimes":[{"profession":"Troubadour","timeMs":675797}]},{"account":"SigmoReborn.4502","characterNames":["Xiggeh"],"combatTimeMs":687206,"squadTimeMs":2602902,"classTimes":[{"profession":"Chronomancer","timeMs":687206}]},{"account":"xavier.7651","characterNames":["Peritzu"],"combatTimeMs":633097,"squadTimeMs":2602902,"classTimes":[{"profession":"Chronomancer","timeMs":633097}]},{"account":"OdinNevon.7305","characterNames":["Sorrow Tonic"],"combatTimeMs":346778,"squadTimeMs":1289897,"classTimes":[{"profession":"Troubadour","timeMs":346778}]},{"account":"Guvno.9612","characterNames":["Guvs Impaired"],"combatTimeMs":385815,"squadTimeMs":920902,"classTimes":[{"profession":"Troubadour","timeMs":385815}]}]}},{"meta":{"id":"20260622-203606-af8b","dateStart":"2026-06-23T01:36:06.000Z","dateEnd":"2026-06-23T02:21:22.000Z","generatedAt":"2026-06-23T02:51:50.972Z"},"stats":{"commanderStats":{"rows":[{"key":"CrimeLordXx.3920","account":"CrimeLordXx.3920","characterNames":["Link Does Damage"],"profession":"Berserker","fights":15,"kills":62,"downs":110,"commanderDeaths":3,"alliesDead":67,"wins":9,"losses":6},{"key":"Opticz.7029","account":"Opticz.7029","characterNames":["Eternalsrs"],"profession":"Scourge","fights":1,"kills":0,"downs":0,"commanderDeaths":0,"alliesDead":6,"wins":0,"losses":1}]},"attendanceData":[{"account":"CowOfGlory.5816","characterNames":["Cow Of Glory"],"combatTimeMs":1299684,"squadTimeMs":3349017,"classTimes":[{"profession":"Evoker","timeMs":1299684}]},{"account":"Deadly Gargoyle.8342","characterNames":["Necroz Bobb"],"combatTimeMs":1225253,"squadTimeMs":3349017,"classTimes":[{"profession":"Harbinger","timeMs":1225253}]},{"account":"EternalEndless.7695","characterNames":["Endless S"],"combatTimeMs":1220238,"squadTimeMs":3349017,"classTimes":[{"profession":"Harbinger","timeMs":1088779},{"profession":"Scourge","timeMs":97556},{"profession":"Necromancer","timeMs":33903}]},{"account":"GaiJai.4759","characterNames":["J J J J J J J J L T"],"combatTimeMs":1306555,"squadTimeMs":3349017,"classTimes":[{"profession":"Druid","timeMs":1306555}]},{"account":"katoki.7869","characterNames":["Luna Du Courte"],"combatTimeMs":1281684,"squadTimeMs":3349017,"classTimes":[{"profession":"Druid","timeMs":1281684}]},{"account":"LFOsc.8930","characterNames":["Oscillating Salad"],"combatTimeMs":1134306,"squadTimeMs":3349017,"classTimes":[{"profession":"Firebrand","timeMs":1134306}]},{"account":"Pieswithattitude.2357","characterNames":["Pie Ele"],"combatTimeMs":1162503,"squadTimeMs":3349017,"classTimes":[{"profession":"Evoker","timeMs":777253},{"profession":"Catalyst","timeMs":334462},{"profession":"Tempest","timeMs":50788}]},{"account":"Skadii.3591","characterNames":["Pearl Leon"],"combatTimeMs":1274023,"squadTimeMs":3349017,"classTimes":[{"profession":"Luminary","timeMs":1274023}]},{"account":"Venguard.2640","characterNames":["Team Captain"],"combatTimeMs":1310700,"squadTimeMs":3349017,"classTimes":[{"profession":"Luminary","timeMs":1310700}]},{"account":"xavier.7651","characterNames":["Peritsu","Reívaxx"],"combatTimeMs":1264316,"squadTimeMs":3349017,"classTimes":[{"profession":"Warrior","timeMs":887913},{"profession":"Catalyst","timeMs":299926},{"profession":"Evoker","timeMs":76477}]},{"account":"Carnibaal.2140","characterNames":["Caarne Asada"],"combatTimeMs":1268211,"squadTimeMs":3306864,"classTimes":[{"profession":"Druid","timeMs":1268211}]},{"account":"CrimeLordXx.3920","characterNames":["Link Does Damage"],"combatTimeMs":1200954,"squadTimeMs":3306864,"classTimes":[{"profession":"Berserker","timeMs":1200954}]},{"account":"curinga.6104","characterNames":["Sea Kalm"],"combatTimeMs":1332183,"squadTimeMs":3306864,"classTimes":[{"profession":"Luminary","timeMs":1332183}]},{"account":"Foodels.7358","characterNames":["Illusionary Oinkies"],"combatTimeMs":1285095,"squadTimeMs":3306864,"classTimes":[{"profession":"Troubadour","timeMs":1285095}]},{"account":"globburt.4139","characterNames":["Glob Of A Dead Star"],"combatTimeMs":1130076,"squadTimeMs":3306864,"classTimes":[{"profession":"Catalyst","timeMs":1130076}]},{"account":"JaNordy.6149","characterNames":["Jatska"],"combatTimeMs":776680,"squadTimeMs":3306864,"classTimes":[{"profession":"Dragonhunter","timeMs":776680}]},{"account":"Max Danger.4031","characterNames":["Purple Beam Go Brrr"],"combatTimeMs":1287527,"squadTimeMs":3306864,"classTimes":[{"profession":"Troubadour","timeMs":1287527}]},{"account":"mikerock.6187","characterNames":["Post Flash Clarity"],"combatTimeMs":1083712,"squadTimeMs":3306864,"classTimes":[{"profession":"Catalyst","timeMs":1083712}]},{"account":"Opticz.7029","characterNames":["Eternalsrs"],"combatTimeMs":1016459,"squadTimeMs":3306864,"classTimes":[{"profession":"Scourge","timeMs":884709},{"profession":"Harbinger","timeMs":131750}]},{"account":"pieddroit.2374","characterNames":["Pedro La Legende"],"combatTimeMs":595886,"squadTimeMs":2310826,"classTimes":[{"profession":"Berserker","timeMs":595886}]},{"account":"Alatreon.1946","characterNames":["Get Off On Me"],"combatTimeMs":779975,"squadTimeMs":2182017,"classTimes":[{"profession":"Troubadour","timeMs":779975}]},{"account":"InvadorGamer.8650","characterNames":["Chi Muelo"],"combatTimeMs":519759,"squadTimeMs":1872826,"classTimes":[{"profession":"Berserker","timeMs":519759}]}]}},{"meta":{"id":"20260622-203606-1pgi","dateStart":"2026-06-23T01:36:06.000Z","dateEnd":"2026-06-23T02:21:22.000Z","generatedAt":"2026-06-23T02:53:35.955Z"},"stats":{"commanderStats":{"rows":[{"key":"CrimeLordXx.3920","account":"CrimeLordXx.3920","characterNames":["Link Does Damage"],"profession":"Berserker","fights":15,"kills":62,"downs":110,"commanderDeaths":3,"alliesDead":67,"wins":9,"losses":6},{"key":"Opticz.7029","account":"Opticz.7029","characterNames":["Eternalsrs"],"profession":"Scourge","fights":1,"kills":0,"downs":0,"commanderDeaths":0,"alliesDead":6,"wins":0,"losses":1}]},"attendanceData":[{"account":"Carnibaal.2140","characterNames":["Caarne Asada"],"combatTimeMs":1268211,"squadTimeMs":3306864,"classTimes":[{"profession":"Druid","timeMs":1268211}]},{"account":"CowOfGlory.5816","characterNames":["Cow Of Glory"],"combatTimeMs":1284677,"squadTimeMs":3306864,"classTimes":[{"profession":"Evoker","timeMs":1284677}]},{"account":"CrimeLordXx.3920","characterNames":["Link Does Damage"],"combatTimeMs":1200954,"squadTimeMs":3306864,"classTimes":[{"profession":"Berserker","timeMs":1200954}]},{"account":"curinga.6104","characterNames":["Sea Kalm"],"combatTimeMs":1332183,"squadTimeMs":3306864,"classTimes":[{"profession":"Luminary","timeMs":1332183}]},{"account":"Deadly Gargoyle.8342","characterNames":["Necroz Bobb"],"combatTimeMs":1210247,"squadTimeMs":3306864,"classTimes":[{"profession":"Harbinger","timeMs":1210247}]},{"account":"EternalEndless.7695","characterNames":["Endless S"],"combatTimeMs":1205231,"squadTimeMs":3306864,"classTimes":[{"profession":"Harbinger","timeMs":1073772},{"profession":"Scourge","timeMs":97556},{"profession":"Necromancer","timeMs":33903}]},{"account":"Foodels.7358","characterNames":["Illusionary Oinkies"],"combatTimeMs":1285095,"squadTimeMs":3306864,"classTimes":[{"profession":"Troubadour","timeMs":1285095}]},{"account":"GaiJai.4759","characterNames":["J J J J J J J J L T"],"combatTimeMs":1291548,"squadTimeMs":3306864,"classTimes":[{"profession":"Druid","timeMs":1291548}]},{"account":"globburt.4139","characterNames":["Glob Of A Dead Star"],"combatTimeMs":1130076,"squadTimeMs":3306864,"classTimes":[{"profession":"Catalyst","timeMs":1130076}]},{"account":"JaNordy.6149","characterNames":["Jatska"],"combatTimeMs":776680,"squadTimeMs":3306864,"classTimes":[{"profession":"Dragonhunter","timeMs":776680}]},{"account":"katoki.7869","characterNames":["Luna Du Courte"],"combatTimeMs":1266677,"squadTimeMs":3306864,"classTimes":[{"profession":"Druid","timeMs":1266677}]},{"account":"LFOsc.8930","characterNames":["Oscillating Salad"],"combatTimeMs":1119300,"squadTimeMs":3306864,"classTimes":[{"profession":"Firebrand","timeMs":1119300}]},{"account":"Max Danger.4031","characterNames":["Purple Beam Go Brrr"],"combatTimeMs":1287527,"squadTimeMs":3306864,"classTimes":[{"profession":"Troubadour","timeMs":1287527}]},{"account":"mikerock.6187","characterNames":["Post Flash Clarity"],"combatTimeMs":1083712,"squadTimeMs":3306864,"classTimes":[{"profession":"Catalyst","timeMs":1083712}]},{"account":"Opticz.7029","characterNames":["Eternalsrs"],"combatTimeMs":1016459,"squadTimeMs":3306864,"classTimes":[{"profession":"Scourge","timeMs":884709},{"profession":"Harbinger","timeMs":131750}]},{"account":"Pieswithattitude.2357","characterNames":["Pie Ele"],"combatTimeMs":1147497,"squadTimeMs":3306864,"classTimes":[{"profession":"Evoker","timeMs":777253},{"profession":"Catalyst","timeMs":319456},{"profession":"Tempest","timeMs":50788}]},{"account":"Skadii.3591","characterNames":["Pearl Leon"],"combatTimeMs":1259016,"squadTimeMs":3306864,"classTimes":[{"profession":"Luminary","timeMs":1259016}]},{"account":"Venguard.2640","characterNames":["Team Captain"],"combatTimeMs":1295693,"squadTimeMs":3306864,"classTimes":[{"profession":"Luminary","timeMs":1295693}]},{"account":"xavier.7651","characterNames":["Peritsu","Reívaxx"],"combatTimeMs":1249309,"squadTimeMs":3306864,"classTimes":[{"profession":"Warrior","timeMs":887913},{"profession":"Catalyst","timeMs":284919},{"profession":"Evoker","timeMs":76477}]},{"account":"pieddroit.2374","characterNames":["Pedro La Legende"],"combatTimeMs":595886,"squadTimeMs":2310826,"classTimes":[{"profession":"Berserker","timeMs":595886}]},{"account":"Alatreon.1946","characterNames":["Get Off On Me"],"combatTimeMs":764969,"squadTimeMs":2139864,"classTimes":[{"profession":"Troubadour","timeMs":764969}]},{"account":"InvadorGamer.8650","characterNames":["Chi Muelo"],"combatTimeMs":519759,"squadTimeMs":1872826,"classTimes":[{"profession":"Berserker","timeMs":519759}]}]}}],"rollup":{"commanderRows":[{"account":"Opticz.7029","characterNames":["Eternalsrs","Get On Me","Jokajo"],"profession":"Scourge","professionBreakdown":[{"profession":"Scourge","runs":1},{"profession":"Troubadour","runs":1}],"runs":2,"fightsLed":12,"kills":10,"downs":51,"commanderDeaths":3,"alliesDead":57,"wins":1,"losses":11,"kdr":0.17543859649122806,"lastSeenTs":1782181282000},{"account":"CrimeLordXx.3920","characterNames":["Link Does Damage"],"profession":"Berserker","professionBreakdown":[{"profession":"Berserker","runs":1}],"runs":1,"fightsLed":15,"kills":62,"downs":110,"commanderDeaths":3,"alliesDead":67,"wins":9,"losses":6,"kdr":0.9253731343283582,"lastSeenTs":1782181282000}],"playerRows":[{"account":"curinga.6104","characterNames":["Sea Kalm"],"profession":"Luminary","professionBreakdown":[{"profession":"Luminary","runs":2}],"runs":2,"combatTimeMs":2064778,"squadTimeMs":5909766,"lastSeenTs":1782181282000},{"account":"EternalEndless.7695","characterNames":["Endless S"],"profession":"Harbinger","professionBreakdown":[{"profession":"Harbinger","runs":2},{"profession":"Necromancer","runs":2},{"profession":"Scourge","runs":1}],"runs":2,"combatTimeMs":1925092,"squadTimeMs":5909766,"lastSeenTs":1782181282000},{"account":"katoki.7869","characterNames":["Luna Du Courte"],"profession":"Druid","professionBreakdown":[{"profession":"Druid","runs":2}],"runs":2,"combatTimeMs":1951209,"squadTimeMs":5909766,"lastSeenTs":1782181282000},{"account":"LFOsc.8930","characterNames":["Am I Oscuro","Oscillating Salad"],"profession":"Firebrand","professionBreakdown":[{"profession":"Chronomancer","runs":1},{"profession":"Firebrand","runs":1}],"runs":2,"combatTimeMs":1760231,"squadTimeMs":5909766,"lastSeenTs":1782181282000},{"account":"Opticz.7029","characterNames":["Eternalsrs","Get On Me","Jokajo"],"profession":"Scourge","professionBreakdown":[{"profession":"Harbinger","runs":1},{"profession":"Scourge","runs":1},{"profession":"Troubadour","runs":1}],"runs":2,"combatTimeMs":1692256,"squadTimeMs":5909766,"lastSeenTs":1782181282000},{"account":"xavier.7651","characterNames":["Peritsu","Peritzu","Reívaxx"],"profession":"Warrior","professionBreakdown":[{"profession":"Catalyst","runs":1},{"profession":"Chronomancer","runs":1},{"profession":"Evoker","runs":1},{"profession":"Warrior","runs":1}],"runs":2,"combatTimeMs":1882406,"squadTimeMs":5909766,"lastSeenTs":1782181282000},{"account":"Alatreon.1946","characterNames":["Alatreon Unendlich","Get Off On Me"],"profession":"Troubadour","professionBreakdown":[{"profession":"Luminary","runs":1},{"profession":"Troubadour","runs":1}],"runs":2,"combatTimeMs":1286666,"squadTimeMs":4742766,"lastSeenTs":1782181282000},{"account":"Carnibaal.2140","characterNames":["Caarne Asada"],"profession":"Druid","professionBreakdown":[{"profession":"Druid","runs":1}],"runs":1,"combatTimeMs":1268211,"squadTimeMs":3306864,"lastSeenTs":1782181282000},{"account":"CowOfGlory.5816","characterNames":["Cow Of Glory"],"profession":"Evoker","professionBreakdown":[{"profession":"Evoker","runs":1}],"runs":1,"combatTimeMs":1284677,"squadTimeMs":3306864,"lastSeenTs":1782181282000},{"account":"CrimeLordXx.3920","characterNames":["Link Does Damage"],"profession":"Berserker","professionBreakdown":[{"profession":"Berserker","runs":1}],"runs":1,"combatTimeMs":1200954,"squadTimeMs":3306864,"lastSeenTs":1782181282000},{"account":"Deadly Gargoyle.8342","characterNames":["Necroz Bobb"],"profession":"Harbinger","professionBreakdown":[{"profession":"Harbinger","runs":1}],"runs":1,"combatTimeMs":1210247,"squadTimeMs":3306864,"lastSeenTs":1782181282000},{"account":"Foodels.7358","characterNames":["Illusionary Oinkies"],"profession":"Troubadour","professionBreakdown":[{"profession":"Troubadour","runs":1}],"runs":1,"combatTimeMs":1285095,"squadTimeMs":3306864,"lastSeenTs":1782181282000},{"account":"GaiJai.4759","characterNames":["J J J J J J J J L T"],"profession":"Druid","professionBreakdown":[{"profession":"Druid","runs":1}],"runs":1,"combatTimeMs":1291548,"squadTimeMs":3306864,"lastSeenTs":1782181282000},{"account":"globburt.4139","characterNames":["Glob Of A Dead Star"],"profession":"Catalyst","professionBreakdown":[{"profession":"Catalyst","runs":1}],"runs":1,"combatTimeMs":1130076,"squadTimeMs":3306864,"lastSeenTs":1782181282000},{"account":"JaNordy.6149","characterNames":["Jatska"],"profession":"Dragonhunter","professionBreakdown":[{"profession":"Dragonhunter","runs":1}],"runs":1,"combatTimeMs":776680,"squadTimeMs":3306864,"lastSeenTs":1782181282000},{"account":"Max Danger.4031","characterNames":["Purple Beam Go Brrr"],"profession":"Troubadour","professionBreakdown":[{"profession":"Troubadour","runs":1}],"runs":1,"combatTimeMs":1287527,"squadTimeMs":3306864,"lastSeenTs":1782181282000},{"account":"mikerock.6187","characterNames":["Post Flash Clarity"],"profession":"Catalyst","professionBreakdown":[{"profession":"Catalyst","runs":1}],"runs":1,"combatTimeMs":1083712,"squadTimeMs":3306864,"lastSeenTs":1782181282000},{"account":"Pieswithattitude.2357","characterNames":["Pie Ele"],"profession":"Evoker","professionBreakdown":[{"profession":"Catalyst","runs":1},{"profession":"Evoker","runs":1},{"profession":"Tempest","runs":1}],"runs":1,"combatTimeMs":1147497,"squadTimeMs":3306864,"lastSeenTs":1782181282000},{"account":"Skadii.3591","characterNames":["Pearl Leon"],"profession":"Luminary","professionBreakdown":[{"profession":"Luminary","runs":1}],"runs":1,"combatTimeMs":1259016,"squadTimeMs":3306864,"lastSeenTs":1782181282000},{"account":"Venguard.2640","characterNames":["Team Captain"],"profession":"Luminary","professionBreakdown":[{"profession":"Luminary","runs":1}],"runs":1,"combatTimeMs":1295693,"squadTimeMs":3306864,"lastSeenTs":1782181282000},{"account":"pieddroit.2374","characterNames":["Pedro La Legende"],"profession":"Berserker","professionBreakdown":[{"profession":"Berserker","runs":1}],"runs":1,"combatTimeMs":595886,"squadTimeMs":2310826,"lastSeenTs":1782181282000},{"account":"InvadorGamer.8650","characterNames":["Chi Muelo"],"profession":"Berserker","professionBreakdown":[{"profession":"Berserker","runs":1}],"runs":1,"combatTimeMs":519759,"squadTimeMs":1872826,"lastSeenTs":1782181282000},{"account":"Celestiaallure.8472","characterNames":["Celestia Allure"],"profession":"Tempest","professionBreakdown":[{"profession":"Tempest","runs":1}],"runs":1,"combatTimeMs":663873,"squadTimeMs":2602902,"lastSeenTs":1781665055000},{"account":"Chewy.5329","characterNames":["Aegisbane"],"profession":"Firebrand","professionBreakdown":[{"profession":"Firebrand","runs":1}],"runs":1,"combatTimeMs":732595,"squadTimeMs":2602902,"lastSeenTs":1781665055000},{"account":"DanIsMyNewName.9826","characterNames":["Dan Is A Name"],"profession":"Harbinger","professionBreakdown":[{"profession":"Harbinger","runs":1}],"runs":1,"combatTimeMs":695294,"squadTimeMs":2602902,"lastSeenTs":1781665055000},{"account":"DoctorBus.8932","characterNames":["Doktor Bus","Unclean Bus"],"profession":"Reaper","professionBreakdown":[{"profession":"Reaper","runs":1},{"profession":"Warrior","runs":1}],"runs":1,"combatTimeMs":657929,"squadTimeMs":2602902,"lastSeenTs":1781665055000},{"account":"Jaxx.8016","characterNames":["Jaxx Wild"],"profession":"Druid","professionBreakdown":[{"profession":"Druid","runs":1}],"runs":1,"combatTimeMs":672998,"squadTimeMs":2602902,"lastSeenTs":1781665055000},{"account":"KaiDarius.8723","characterNames":["Lucent Dreams"],"profession":"Chronomancer","professionBreakdown":[{"profession":"Chronomancer","runs":1}],"runs":1,"combatTimeMs":529862,"squadTimeMs":2602902,"lastSeenTs":1781665055000},{"account":"Kricer.7253","characterNames":["Let It Krice"],"profession":"Troubadour","professionBreakdown":[{"profession":"Troubadour","runs":1}],"runs":1,"combatTimeMs":704487,"squadTimeMs":2602902,"lastSeenTs":1781665055000},{"account":"lightofday.9173","characterNames":["Light Algz"],"profession":"Firebrand","professionBreakdown":[{"profession":"Firebrand","runs":1}],"runs":1,"combatTimeMs":707017,"squadTimeMs":2602902,"lastSeenTs":1781665055000},{"account":"MasterVance.6201","characterNames":["Van Snacks"],"profession":"Reaper","professionBreakdown":[{"profession":"Reaper","runs":1}],"runs":1,"combatTimeMs":571790,"squadTimeMs":2602902,"lastSeenTs":1781665055000},{"account":"MoonRaven.3142","characterNames":["Illusive Heart"],"profession":"Troubadour","professionBreakdown":[{"profession":"Troubadour","runs":1}],"runs":1,"combatTimeMs":665729,"squadTimeMs":2602902,"lastSeenTs":1781665055000},{"account":"Nina.9521","characterNames":["Labubù"],"profession":"Scourge","professionBreakdown":[{"profession":"Scourge","runs":1}],"runs":1,"combatTimeMs":719679,"squadTimeMs":2602902,"lastSeenTs":1781665055000},{"account":"SigmoReborn.4502","characterNames":["Xiggeh"],"profession":"Chronomancer","professionBreakdown":[{"profession":"Chronomancer","runs":1}],"runs":1,"combatTimeMs":687206,"squadTimeMs":2602902,"lastSeenTs":1781665055000},{"account":"OdinNevon.7305","characterNames":["Sorrow Tonic"],"profession":"Troubadour","professionBreakdown":[{"profession":"Troubadour","runs":1}],"runs":1,"combatTimeMs":346778,"squadTimeMs":1289897,"lastSeenTs":1781665055000},{"account":"Guvno.9612","characterNames":["Guvs Impaired"],"profession":"Troubadour","professionBreakdown":[{"profession":"Troubadour","runs":1}],"runs":1,"combatTimeMs":385815,"squadTimeMs":920902,"lastSeenTs":1781665055000}],"sourceReports":3,"uniqueRaids":2,"duplicateReportsCollapsed":1,"raidsSkippedMissingRequiredData":0,"reportsWithCommanderDetails":2,"reportsMissingCommanderDetails":0,"reportsWithAttendanceDetails":2,"reportsMissingAttendanceDetails":0}}